kanone/__init__.py
kanone/error.py
kanone/lib.py
kanone/adapter/__init__.py
kanone/adapter/native.py
kanone/adapter/pylons.py
kanone/adapter/tx.py
kanone/util/__init__.py
kanone/validator/__init__.py
kanone/validator/alter.py
kanone/validator/basic.py
kanone/validator/cache.py
kanone/validator/check.py
kanone/validator/core.py
kanone/validator/debug.py
kanone/validator/schema.py
kanone/validator/web.py
kanone-0.4.6.dist-info/METADATA
kanone-0.4.6.dist-info/WHEEL
kanone-0.4.6.dist-info/namespace_packages.txt
kanone-0.4.6.dist-info/top_level.txt
kanone-0.4.6.dist-info/RECORD
