Metadata-Version: 2.1
Name: kanone
Version: 0.4.6
Summary: a validation library
Home-page: http://github.com/doncatnip/kanone
Author: don`catnip
Author-email: UNKNOWN
License: Unlicense
Keywords: validation library form twisted stateful
Platform: UNKNOWN
Classifier: Development Status :: 4 - Beta
Classifier: Topic :: Software Development :: Libraries :: Python Modules
Classifier: License :: Public Domain
Classifier: Programming Language :: Python :: 2.7
Classifier: Programming Language :: Python :: 3
Classifier: Intended Audience :: Developers
